sdk_test_sdk/__init__.py
sdk_test_sdk/core.py
sdk_test_sdk-2.0.0.dist-info/LICENSE.txt
sdk_test_sdk-2.0.0.dist-info/METADATA
sdk_test_sdk-2.0.0.dist-info/WHEEL
sdk_test_sdk-2.0.0.dist-info/top_level.txt
sdk_test_sdk-2.0.0.dist-info/RECORD
