Metadata-Version: 2.1
Name: sdk-test-sdk
Version: 2.0.0
Summary: An awesome SDK to say hello!
Home-page: https://github.com/your/repo
Author: Your Name
Author-email: your@email.com
License: MIT
Keywords: python sample project example
Platform: UNKNOWN
Classifier: Programming Language :: Python :: 3
Classifier: License :: OSI Approved :: MIT License
Classifier: Operating System :: OS Independent
Requires-Python: >=3.6
License-File: LICENSE.txt
Requires-Dist: numpy (==1.24.4)
